MANIFEST.in
README.txt
setup.py
c2/__init__.py
c2.manage.sharesetting.egg-info/PKG-INFO
c2.manage.sharesetting.egg-info/SOURCES.txt
c2.manage.sharesetting.egg-info/dependency_links.txt
c2.manage.sharesetting.egg-info/entry_points.txt
c2.manage.sharesetting.egg-info/namespace_packages.txt
c2.manage.sharesetting.egg-info/not-zip-safe
c2.manage.sharesetting.egg-info/requires.txt
c2.manage.sharesetting.egg-info/top_level.txt
c2/manage/__init__.py
c2/manage/sharesetting/__init__.py
c2/manage/sharesetting/configure.zcml
c2/manage/sharesetting/tests.py
c2/manage/sharesetting/version.txt
c2/manage/sharesetting/browser/__init__.py
c2/manage/sharesetting/browser/configure.zcml
c2/manage/sharesetting/browser/sharesetting.pt
c2/manage/sharesetting/browser/sharesetting.py
c2/manage/sharesetting/browser/sharesetting_macro.pt
c2/manage/sharesetting/profiles/default/controlpanel.xml
c2/manage/sharesetting/profiles/default/metadata.xml
docs/HISTORY.txt
docs/INSTALL.txt
docs/LICENSE.GPL
docs/LICENSE.txt