Metadata-Version: 1.1
Name: c2.manage.sharesetting
Version: 1.0
Summary: Managing local roles setting for Plone site
Home-page: http://www.cmscom.jp
Author: Manabu TERADA
Author-email: terada@cmscom.jp
License: GPL
Keywords: plone manage setting share
Platform: UNKNOWN
Classifier: Framework :: Plone
Classifier: Programming Language :: Python
